pyxbarr/__init__.py
pyxbarr/item/__init__.py
pyxbarr/item/divider.py
pyxbarr/item/attribute/__base__.py
pyxbarr/item/attribute/__init__.py
pyxbarr/item/attribute/alternative.py
pyxbarr/item/attribute/ansi.py
pyxbarr/item/attribute/color.py
pyxbarr/item/attribute/disabled.py
pyxbarr/item/attribute/dropdown.py
pyxbarr/item/attribute/emojize.py
pyxbarr/item/attribute/font.py
pyxbarr/item/attribute/href.py
pyxbarr/item/attribute/image.py
pyxbarr/item/attribute/key.py
pyxbarr/item/attribute/length.py
pyxbarr/item/attribute/parmas.py
pyxbarr/item/attribute/refresh.py
pyxbarr/item/attribute/shell.py
pyxbarr/item/attribute/size.py
pyxbarr/item/attribute/template_image.py
pyxbarr/item/attribute/terminal.py
pyxbarr/item/attribute/trim.py
pyxbarr/plugin/__init__.py
pyxbarr/section/__init__.py
pyxbarr-0.0.2.dist-info/METADATA
pyxbarr-0.0.2.dist-info/WHEEL
pyxbarr-0.0.2.dist-info/licenses/LICENSE
pyxbarr-0.0.2.dist-info/RECORD
