Metadata-Version: 2.3
Name: pyxbarr
Version: 0.0.2
Summary: A python utility for creating xbar menus.
Project-URL: Homepage, https://github.com/gohadar/pyxbarr
Author-email: Hadar Gotshal <gohadar@gmail.com>
Maintainer-email: Hadar Gotshal <gohadar@gmail.com>
License-Expression: Apache-2.0
License-File: LICENSE
Classifier: Intended Audience :: Developers
Classifier: Operating System :: OS Independent
Classifier: Programming Language :: Python
Classifier: Programming Language :: Python :: 3
Classifier: Programming Language :: Python :: 3.8
Classifier: Programming Language :: Python :: 3.9
Classifier: Programming Language :: Python :: 3.10
Classifier: Programming Language :: Python :: 3.11
Requires-Python: >=3.7
